{
  "artistas": [
    {
      "id": "oscar-spiker",
      "name": "Oscar",
      "artistName": "Spiker",
      "experienceYears": 10,
      "bio": "Especialista en realismo detallado con 10 años de experiencia",
      "estilos": ["realismo", "blackwork", "japones", "geometrico"],
      "ubicacion": "Guadalajara, Jalisco",
      "imagen": "../public/img/tatuadores/spiker.webp",
      "redes": {
        "instagram": "https://instagram.com/spiker_tattoo",
        "whatsapp": "+5213312345678"
      }
    },
    {
      "id": "Chino",
      "name": "El Chino",
      "artistName": "PARCKETECK",
      "experienceYears": 8,
      "bio": "Artista de tatuajes con enfoque en old school y color vibrante",
      "estilos": ["old school", "color", "neo tradicional", "portrait"],
      "ubicacion": "Guadalajara, Jalisco",
      "imagen": "../public/img/tatuadores/perckateck.jpg",
      "redes": {
        "instagram": "https://instagram.com/luna_tattoo_art",
        "whatsapp": "+5213312345679"
      }
    },
    {
      "id": "Comper",
      "name": "Casiel",
      "artistName": "Compendium",
      "experienceYears": 5,
      "bio": "Maestro en linework y blackwork minimalista",
      "estilos": ["blackwork", "linework", "minimal", "geometrico"],
      "ubicacion": "Guadalajara, Jalisco",
      "imagen": "../public/img/tatuadores/compe.webp",
      "redes": {
        "instagram": "https://instagram.com/black_ink_tattoo",
        "whatsapp": "+5213312345680"
      }
    },
    {
      "id": "EL ALONSO",
      "name": "ALONSO",
      "artistName": "EL ALONSO",
      "experienceYears": 6,
      "bio": "Especialista en dotwork y tatuajes de punto fino",
      "estilos": ["dotwork", "minimal", "japones", "geometrico"],
      "ubicacion": "Guadalajara, Jalisco",
      "imagen": "../public/img/tatuadores/ELALONSO.jpg",
      "redes": {
        "instagram": "https://instagram.com/dot_tattoo_art",
        "whatsapp": "+5213312345681"
      }
    }
  
  ]
}